FlowMetricsCSV/CsvService.py
FlowMetricsCSV/ExampleConfig.json
FlowMetricsCSV/ExampleFile.csv
FlowMetricsCSV/FlowMetricsService.py
FlowMetricsCSV/WorkItem.py
FlowMetricsCSV/__init__.py
FlowMetricsCSV/logo.png
FlowMetricsCSV/main.py
flowmetricscsv-1.0.5.dist-info/LICENSE
flowmetricscsv-1.0.5.dist-info/METADATA
flowmetricscsv-1.0.5.dist-info/WHEEL
flowmetricscsv-1.0.5.dist-info/entry_points.txt
flowmetricscsv-1.0.5.dist-info/top_level.txt
flowmetricscsv-1.0.5.dist-info/RECORD
