Metadata-Version: 2.2
Name: flowmetricscsv
Version: 1.0.5
Summary: A package to generate flow metrics charts from CSV files.
Home-page: https://letpeople.work
Author: Benjamin Huser-Berta
Author-email: benj.huser@gmail.com
Classifier: Programming Language :: Python :: 3
Classifier: License :: OSI Approved :: MIT License
Classifier: Operating System :: OS Independent
Requires-Python: >=3.6
License-File: LICENSE
Requires-Dist: argparse
Requires-Dist: pandas
Requires-Dist: numpy
Requires-Dist: matplotlib
Requires-Dist: adjustText
Dynamic: author
Dynamic: author-email
Dynamic: classifier
Dynamic: description
Dynamic: description-content-type
Dynamic: home-page
Dynamic: requires-dist
Dynamic: requires-python
Dynamic: summary
